{"status": "ok", "totalResults": 58, "articles": [{"source": {"id": null, "name": "Moneycontrol"}, "author": "Hindi.Moneycontrol.com Team, Moneycontrol Hindi", "title": "Share Market Live Update: SGX NIFTY \u0926\u0947 \u0930\u0939\u093e \u0938\u0902\u0915\u0947\u0924, \u092e\u091c\u092c\u0942\u0924 \u0939\u094b \u0938\u0915\u0924\u0940 \u0939\u0948 \u092d\u093e\u0930\u0924\u0940\u092f \u092c\u093e\u091c\u093e\u0930 \u0915\u0940 \u0936\u0941\u0930\u0941\u0906\u0924", "description": "Share Market Live Update-\u00a0\n\n\u090f\u0936\u093f\u092f\u093e, SGX NIFTY \u0914\u0930 DOW FUTURES \u092e\u0947\u0902 \u092e\u091c\u092c\u0942\u0924\u0940\n\n\u0939\u092b\u094d\u0924\u0947 \u0915\u0947 \u092a\u0939\u0932\u0947 \u0926\u093f\u0928 \u0917\u094d\u0932\u094b\u092c\u0932 \u092e\u093e\u0930\u094d\u0915\u0947\u091f \u0938\u0947 \u0938\u0902\u0915\u0947\u0924 \u0905\u091a\u094d\u091b\u0947 \u0928\u091c\u0930 \u0906 \u0930\u0939\u0947 \u0939\u0948\u0964 \u090f\u0936\u093f\u092f\u093e \u0915\u0940 \u092e\u091c\u092c\u0942\u0924 \u0936\u0941\u0930\u0941\u0906\u0924 \u0939\u0941\u0908 \u0939\u0948\u0964 SGX NIFTY \u092e\u0947\u0902 100 \u0905\u0902\u0915\u094b\u0902 \u0909\u091b\u093e\u0932 \u0926\u0947\u0916\u0928\u0947 \u0915\u094b \u092e\u093f\u0932 \u0930\u0939\u093e \u0939\u0948\u0964 DOW FUTURES \u092d\u0940 \u0915\u0930\u0940\u092c 250 POINT \u090a\u092a\u0930 \u0928\u091c\u0930 \u0906 \u0930\u0939\u093e \u0939\u2026", "url": "http://hindi.moneycontrol.com/news/markets/share-market-live-updates-stock-market-today-may-23-latest-news-bse-nse-sensex-nifty-coronavirus-hpcl-bpcl-ioc-585401.html", "urlToImage": "https://images.moneycontrol.com/static-hindinews/2022/05/bullbear-6.jpg", "publishedAt": "2022-05-23T02:52:49Z", "content": "20 5 - 3 2 2 - \r\n 1,532.77 2.90 54,326.39 484.05 3.06 16,266.2"}, {"source": {"id": null, "name": "Moneycontrol"}, "author": "Moneycontrol News", "title": "MC Insider: Message in a T-shirt, sarkari moves after LIC IPO, brokerage gunning for ETFs, NBFC wary about fintech, and more", "description": "NULL", "url": "https://www.moneycontrol.com/news/business/companies/mc-insider-message-in-a-t-shirt-sarkari-moves-after-lic-ipo-brokerage-gunning-for-etfs-nbfc-wary-about-fintech-and-more-8554931.html", "urlToImage": "https://images.moneycontrol.com/static-mcnews/2020/08/absolutvision-bSlHKWxxXak-unsplash-652x435.jpg", "publishedAt": "2022-05-23T02:27:41Z", "content": "AH, THE IRONY\r\nAt a recent advertising industry award show, some attendees were left puzzled and bothered by the treatment given to a session on diversity, equality and inclusion, a pressing issue fo\u2026 [+343 chars]"}, {"source": {"id": null, "name": "Moneycontrol"}, "author": "Reuters", "title": "Oil climbs in tight market as US driving season looms", "description": "Brent crude futures rose 82 cents to $113.37 a barrel at 0126 GMT, while U.S. West Texas Intermediate (WTI) crude futures climbed 69 cents, or 0.6%, to $110.97 a barrel, adding to last week#39;s small gains for both contracts.", "url": "https://www.moneycontrol.com/news/business/markets/oil-climbs-in-tight-market-as-us-driving-season-looms-8555051.html", "urlToImage": "https://images.moneycontrol.com/static-mcnews/2022/05/Oil-rig-770x433.jpg", "publishedAt": "2022-05-23T02:27:09Z", "content": "Oil prices rose in early trade on Monday with U.S. fuel demand, tight supply and a slightly weaker U.S. dollar supporting the market, as Shanghai prepares to reopen after a two-month lockdown fuelled\u2026 [+1768 chars]"}, {"source": {"id": null, "name": "Moneycontrol"}, "author": "Bloomberg", "title": "After meltdown, tech-bottom signals have yet to scream \u00e2\u0080\u0098buy now\u00e2\u0080\u0099", "description": "Tech stocks have been hammered this year as rising interest rates, slowing economic growth and soaring inflation form a perfect storm of negative catalysts.", "url": "https://www.moneycontrol.com/news/world/after-meltdown-tech-bottom-signals-have-yet-to-scream-buy-now-8555021.html", "urlToImage": "https://images.moneycontrol.com/static-mcnews/2022/05/387516310-770x433.jpg", "publishedAt": "2022-05-23T02:23:08Z", "content": "Calling the bottom in the tech-sector meltdown isnt easy, even after a $5.5 trillion wipe-out, yet there are some signals giving investors hope.\r\nTech stocks have been hammered this year as rising in\u2026 [+5047 chars]"}, {"source": {"id": null, "name": "Moneycontrol"}, "author": "Sandip Das", "title": "Top 10 things to know before the market opens today", "description": "Trends in SGX Nifty indicate a flat opening for the broader index in India with a gain of 5 points", "url": "https://www.moneycontrol.com/news/business/markets/top-10-things-to-know-before-the-market-opens-today-82-8554511.html", "urlToImage": "https://images.moneycontrol.com/static-mcnews/2020/01/BSE_Sensex_Stocks_market-770x433.png", "publishedAt": "2022-05-23T02:20:52Z", "content": "The market is expected to open on a cautious note as\u00a0trends in SGX Nifty indicate a\u00a0flat\u00a0opening for the broader index in India with a\u00a0gain\u00a0of\u00a05\u00a0points.\r\nThe BSE Sensex climbed 1,534 points to 54,326\u2026 [+6174 chars]"}, {"source": {"id": null, "name": "Moneycontrol"}, "author": "Sunil Shankar Matkar", "title": "Top 10 trading ideas from experts for next 3-4 weeks as market snaps five-week losing streak", "description": "The broader market has started to show some encouraging signs, with the Nifty Midcap 100 and Smallcap 100 indices rising 3 percent and 4 percent. This should do extremely well if the market remains above the psychological support of 16,000", "url": "https://www.moneycontrol.com/news/business/markets/top-10-trading-ideas-from-experts-for-next-3-4-weeks-as-market-snaps-five-week-losing-streak-8554581.html", "urlToImage": "https://images.moneycontrol.com/static-mcnews/2022/05/sensex1-1-770x433.jpg", "publishedAt": "2022-05-23T02:09:59Z", "content": "The market snapped a five-week losing streak and closed 3 percent higher in the week ended May 20. Volatility remained on the higher side amid the Ukraine-Russia crisis, and fear of aggressive rate h\u2026 [+8443 chars]"}, {"source": {"id": null, "name": "Moneycontrol"}, "author": "CNBC-TV18", "title": "Threat of recession is real in emerging countries, but things look better for India: President of World Economic Forum", "description": "The meeting will bring together nearly 2,500 global leaders to address current challenges during this time of heightened polarization.", "url": "https://www.moneycontrol.com/news/world/threat-of-recession-is-real-in-emerging-countries-but-things-look-better-for-india-president-of-world-economic-forum-8554941.html", "urlToImage": "https://images.moneycontrol.com/static-mcnews/2017/05/GDP_Growth_Economy_Growth_inflation_recession1-770x433.jpg", "publishedAt": "2022-05-23T02:00:36Z", "content": "The threat of recession is real, especially in developing and emerging countries, but in India, things look better, said Borge Brende, President of the World Economic Forum.\r\nTalking about the intere\u2026 [+1589 chars]"}, {"source": {"id": null, "name": "Moneycontrol"}, "author": "PTI", "title": "PM Modi to attend launch event of IPEF in Tokyo today", "description": "Modi left for Japan on Sunday evening primarily to attend the second in-person summit of the Quad leaders on May 24.", "url": "https://www.moneycontrol.com/news/india/pm-modi-to-attend-launch-event-of-ipef-in-tokyo-today-8554871.html", "urlToImage": "https://images.moneycontrol.com/static-mcnews/2022/04/4-modi-kashmir-visit-770x433.jpg", "publishedAt": "2022-05-23T01:31:57Z", "content": "Prime Minister Narendra Modi on Monday will attend an event in Tokyo where US President Joe Biden will launch the ambitious Indo-Pacific Economic Framework for Prosperity (IPEF), an initiative aimed \u2026 [+2648 chars]"}, {"source": {"id": null, "name": "Moneycontrol"}, "author": "Reuters", "title": "Paytm payments bank expects central bank curbs to be lifted in three-five months", "description": "In March, the Reserve Bank of India ordered a comprehensive audit of the company's IT systems, citing &quot;material&quot; supervisory concerns, without elaborating further, and barring it from taking on new customers.", "url": "https://www.moneycontrol.com/news/business/paytm-payments-bank-expects-central-bank-curbs-to-be-lifted-in-three-five-months-8554851.html", "urlToImage": "https://images.moneycontrol.com/static-mcnews/2020/05/PAYTM-Payments-Bank_-770x433.png", "publishedAt": "2022-05-23T01:22:18Z", "content": "India's Paytm Payments Bank, which facilitates transactions on mobile commerce platform Paytm, expects the central bank to allow it to resume taking on new customers in the next few months, a top exe\u2026 [+1691 chars]"}, {"source": {"id": null, "name": "Moneycontrol"}, "author": "Reuters", "title": "Indian steelmakers face hit on Europe deals over export tax: JSPL executive", "description": "India imposed an export tax of 15% on eight steel products late on Saturday, at a time steelmakers are looking to make up for tepid local demand by increasing market share in Europe, whose supplies have been hit by Russia#39;s invasion of Ukraine.", "url": "https://www.moneycontrol.com/news/business/indian-steelmakers-face-hit-on-europe-deals-over-export-tax-jspl-executive-8554841.html", "urlToImage": "https://images.moneycontrol.com/static-mcnews/2022/05/steel-770x433.jpg", "publishedAt": "2022-05-23T01:20:50Z", "content": "Indian steel firms could be forced to cancel European orders and suffer losses after an overnight decision to impose export taxes on steel products, V R Sharma, managing director at Jindal Steel and \u2026 [+1914 chars]"}, {"source": {"id": null, "name": "Moneycontrol"}, "author": "Reuters", "title": "General Atlantic plans $2 billion investment in India, Southeast Asia", "description": "General Atlantic is in early-stage investment talks with about 15 companies in sectors including technology, financial services, retail and consumer, Sandeep Naik, the head of its business in India and Southeast Asia, said in an interview.", "url": "https://www.moneycontrol.com/news/business/general-atlantic-plans-2-billion-investment-in-india-southeast-asia-8554831.html", "urlToImage": "https://images.moneycontrol.com/static-mcnews/2021/07/dollar-758x435.jpg", "publishedAt": "2022-05-23T01:18:59Z", "content": "Global private equity firm General Atlantic plans to plough $2 billion into India and Southeast Asia over the next two years after falling valuations made the region's startups more attractive, a sen\u2026 [+2133 chars]"}, {"source": {"id": null, "name": "Moneycontrol"}, "author": "Shubham Agarwal", "title": "Deploy modified call butterfly strategy in Nifty: Shubham Agarwal", "description": "Considering the negative momentum, the upcoming week can be approached with a low-risk strategy like modified call butterfly in Nifty.", "url": "https://www.moneycontrol.com/news/trends/expert-columns/deploy-modified-call-butterfly-strategy-in-nifty-shubham-agarwal-15-8549631.html", "urlToImage": "https://images.moneycontrol.com/static-mcnews/2021/04/fandoderivativesensexniftyfutureoption-770x433.jpg", "publishedAt": "2022-05-23T01:16:51Z", "content": "Shubham Agarwal\r\nMomentum shift witnessed from bearish to bullish in Nifty as it rebounds from 15,700 again and it closed the week on a positive note around 16,275 with significant gain of around 3 p\u2026 [+2778 chars]"}, {"source": {"id": null, "name": "Moneycontrol"}, "author": "Reuters", "title": "Gold hits over 1-week high as US dollar dips", "description": "Spot gold rose 0.3% to $1,850.39 per ounce, by 0039 GMT, their highest since May 12. U.S. gold futures GCv1 also gained 0.3% to $1,847.90.", "url": "https://www.moneycontrol.com/news/business/markets/gold-hits-over-1-week-high-as-us-dollar-dips-8554821.html", "urlToImage": "https://images.moneycontrol.com/static-mcnews/2022/05/Gold-770x433.png", "publishedAt": "2022-05-23T01:07:15Z", "content": "Gold prices touched a more than one-week high on Monday, as an easing dollar supported greenback-priced bullion, although rising U.S. Treasury yields capped gains.\r\nFUNDAMENTALS\r\nSpot gold rose 0.3% \u2026 [+1485 chars]"}, {"source": {"id": null, "name": "Moneycontrol"}, "author": "Reuters", "title": "US dollar wobbles lower as China growth hopes lift Aussie", "description": "U.S stock market futures bounced sharply in early Asia trade and pulled the risk-sensitive Australian and New Zealand dollars along for the ride.", "url": "https://www.moneycontrol.com/news/world/us-dollar-wobbles-lower-as-china-growth-hopes-lift-aussie-8554801.html", "urlToImage": "https://images.moneycontrol.com/static-mcnews/2020/11/US-DOLLAR-CURRENCY-770x433.jpg", "publishedAt": "2022-05-23T01:02:50Z", "content": "The dollar began the week on the back foot, following its first weekly loss in nearly two months, as investors cut bets on further dollar gains from rising U.S. rates and turned hopeful that loosenin\u2026 [+2987 chars]"}, {"source": {"id": null, "name": "Moneycontrol"}, "author": "Moneycontrol News", "title": "NSE adds BHEL as fifth stock to FO ban list for Monday", "description": "During the ban, traders are not allowed to take fresh positions in stocks but can start reducing their positions. The ban helps reduce speculation in stocks.", "url": "https://www.moneycontrol.com/news/business/markets/nse-adds-bhel-as-fifth-stock-to-fo-ban-list-for-monday-8554731.html", "urlToImage": "https://images.moneycontrol.com/static-mcnews/2022/05/stocks_sensex_nifty_stockmarket1-2-1-770x431.jpg", "publishedAt": "2022-05-23T00:54:26Z", "content": "The National Stock Exchange has decided to add Bharat Heavy Electricals\u00a0Ltd (BHEL) as the fifth stock on its F&amp;O ban list for May 23 after the scrip crossed 95 percent of the market-wide position\u2026 [+1556 chars]"}, {"source": {"id": null, "name": "Moneycontrol"}, "author": "PTI", "title": "Bring down excise duty on petrol, diesel to UPA-era level: Ashok Gehlot to Centre", "description": "Ashok Gehlot remarks came a day after the government cut the excise duty on petrol by a record Rs 8 per litre and that on diesel by Rs 6 per litre to give relief to consumers grappling with high fuel prices that have also pushed inflation to a record high.", "url": "https://www.moneycontrol.com/news/politics/bring-down-excise-duty-on-petrol-diesel-to-upa-era-level-ashok-gehlot-to-centre-8554781.html", "urlToImage": "https://images.moneycontrol.com/static-mcnews/2022/03/pjimage-6-2-770x433.jpg", "publishedAt": "2022-05-23T00:51:06Z", "content": "Rajasthan Chief Minister Ashok Gehlot on Sunday said the Centre should bring down the excise duty on petrol and diesel to the level it was during the Congress-led UPA government so that common people\u2026 [+1507 chars]"}, {"source": {"id": null, "name": "Moneycontrol"}, "author": "Sunil Shankar Matkar", "title": "Trade Spotlight | What should you do with Granules India, Welspun Corp, JK Lakshmi Cement on Monday?", "description": "Currently JK Lakshmi Cement is well placed above 20, 50 and 100 day SMA. The daily weekly strength indicator RSI is in bullish terrain which supports rising momentum. The daily &quot;band Bollinger&quot; buy signal indicates increased momentum.", "url": "https://www.moneycontrol.com/news/business/markets/trade-spotlight-what-should-you-do-with-granules-india-welspun-corp-jk-lakshmi-cement-on-monday-8551691.html", "urlToImage": "https://images.moneycontrol.com/static-mcnews/2022/05/stocks_sensex_nifty-770x433.jpg", "publishedAt": "2022-05-23T00:48:26Z", "content": "The market rebounded quite sharply and recouped all its previous two-day losses in one single session on May 20 as the benchmark indices rallied nearly\u00a0three percent, supported by positive global tre\u2026 [+3843 chars]"}, {"source": {"id": null, "name": "Moneycontrol"}, "author": "Reuters", "title": "Asia markets tussle with inflation and rates concerns", "description": "MSCI#39;s broadest index of Asia-Pacific shares outside Japan was 0.04% higher, after U.S. stocks ended the previous session with negligible gains for the day. The index is down 3.6% so far this month.", "url": "https://www.moneycontrol.com/news/business/markets/asia-markets-tussle-with-inflation-and-rates-concerns-8554791.html", "urlToImage": "https://images.moneycontrol.com/static-mcnews/2017/03/asian-markets-new-770x433.jpg", "publishedAt": "2022-05-23T00:45:47Z", "content": "Asian stocks faced an uncertain start on Monday as persistent inflation fears and the prospect of rising interest rates dogged the global economic outlook, which remains mired in negative sentiment.\r\u2026 [+2694 chars]"}, {"source": {"id": null, "name": "Moneycontrol"}, "author": "Reuters", "title": "Broadcom in talks to acquire VMware: Sources", "description": "Negotiations between Broadcom and VMware are ongoing and a deal is not imminent, the sources said. The deal terms under discussion could not be learned.", "url": "https://www.moneycontrol.com/news/world/broadcom-in-talks-to-acquire-vmware-sources-8554751.html", "urlToImage": "https://images.moneycontrol.com/static-mcnews/2022/04/broadcom-770x433.jpg", "publishedAt": "2022-05-23T00:40:30Z", "content": "Chipmaker Broadcom Inc is in talks to acquire cloud service provider VMware Inc, people familiar with the matter told Reuters.\r\nNegotiations between Broadcom and VMware are ongoing and a deal is not \u2026 [+1009 chars]"}, {"source": {"id": null, "name": "Moneycontrol"}, "author": "Reuters", "title": "More than 100 million people forcibly displaced in the world: UN", "description": "The war in Ukraine has been one of the factors propelling millions of people to flee, the UNHCR said, adding that protracted conflict in places like Ethiopia and Democratic Republic of Congo were other factors behind the high numbers.", "url": "https://www.moneycontrol.com/news/world/more-than-100-million-people-forcibly-displaced-in-the-world-un-8554741.html", "urlToImage": "https://images.moneycontrol.com/static-mcnews/2022/02/pjimage-2022-02-22T101144.987-770x433.jpg", "publishedAt": "2022-05-23T00:38:41Z", "content": "More than 100 million people have been driven from their homes around the world, the U.N. refugee agency (UNHCR) said on Monday, citing new data about those escaping violence, conflict, persecution a\u2026 [+1249 chars]"}]}