{"status": "ok", "totalResults": 1619, "articles": [{"source": {"id": "the-times-of-india", "name": "The Times of India"}, "author": "ET Spotlight Special", "title": "Telangana board SSC results 2022 is likely to be out soon", "description": "The SSC evaluation for 2022 was completed last week, and BSE Telangana has announced a tentative date for the declaration of the results. As per reports, the TS SSC Board Result 2022 can be declared anywhere by June 25.", "url": "https://economictimes.indiatimes.com/news/new-updates/telangana-board-ssc-results-2022-is-likely-to-be-out-soon/articleshow/92362365.cms", "urlToImage": "https://img.etimg.com/thumb/msid-92364276,width-1070,height-580,imgsize-19596,overlay-economictimes/photo.jpg", "publishedAt": "2022-06-21T12:33:04Z", "content": "Board Of Secondary Education of Telangana announced that they would soon announce the TS SSC Board Result 2022. The evaluation for the same exam was completed last week. As per reports, TS SSC Board \u2026 [+1585 chars]"}, {"source": {"id": "the-times-of-india", "name": "The Times of India"}, "author": "PTI", "title": "Indian women's U-17 football team faces tough Italy test", "description": "Indian women's football team will begin its preparation for the upcoming FIFA U-17 World Cup by taking on Italy in a four-nation tournament at the Gradisca d'lsonzo Stadium on Wednesday.", "url": "https://timesofindia.indiatimes.com/sports/football/top-stories/indian-womens-u-17-football-team-faces-tough-italy-test/articleshow/92364248.cms", "urlToImage": "https://static.toiimg.com/thumb/msid-92364252,width-1070,height-580,imgsize-122056,resizemode-75,overlay-toi_sw,pt-32,y_pad-40/photo.jpg", "publishedAt": "2022-06-21T12:32:16Z", "content": ""}, {"source": {"id": "the-times-of-india", "name": "The Times of India"}, "author": null, "title": "\u0915\u094d\u092f\u093e \u090f\u0915\u0928\u093e\u0925 \u0936\u093f\u0902\u0926\u0947 \u090f\u0928\u0938\u0940\u092a\u0940-\u0936\u093f\u0935\u0938\u0947\u0928\u093e-\u0915\u093e\u0902\u0917\u094d\u0930\u0947\u0938 \u0917\u0920\u092c\u0902\u0927\u0928 \u0915\u0940 \u0938\u092c\u0938\u0947 \u0915\u092e\u091c\u094b\u0930 \u0915\u0921\u093c\u0940 \u0925\u0947?", "description": "\u090f\u0915\u0928\u093e\u0925 \u0936\u093f\u0902\u0926\u0947 \u0915\u093e \u0938\u092b\u0930 \u0926\u0941\u0936\u094d\u200d\u0935\u093e\u0930\u093f\u092f\u094b\u0902 \u0938\u0947 \u092d\u0930\u093e \u0930\u0939\u093e \u0939\u0948\u0964 \u0909\u0928\u094d\u200d\u0939\u094b\u0902\u0928\u0947 \u091c\u0940\u0935\u0928 \u0915\u0947 \u0915\u0908 \u092c\u0921\u093c\u0947 \u0909\u0924\u093e\u0930-\u091a\u0922\u093c\u093e\u0935 \u0926\u0947\u0916\u0947 \u0939\u0948\u0902\u0964 \u092e\u0939\u093e\u0930\u093e\u0937\u094d\u200d\u091f\u094d\u0930 \u0915\u0947 \u0930\u093e\u091c\u0928\u0940\u0924\u093f\u0915 \u0938\u0902\u0915\u091f \u092e\u0947\u0902 \u0909\u0928\u0915\u093e \u0928\u093e\u092e \u0915\u0947\u0902\u0926\u094d\u0930 \u092e\u0947\u0902 \u0939\u0948\u0964 \u0936\u093f\u0902\u0926\u0947 \u091b\u0917\u0928 \u092d\u0941\u091c\u092c\u0932 \u0914\u0930 \u0928\u093e\u0930\u093e\u092f\u0923 \u0930\u093e\u0923\u0947 \u0938\u0930\u0940\u0916\u0947 \u0928\u0947\u0924\u093e\u0913\u0902 \u0915\u0940 \u0930\u093e\u0939 \u092a\u0930 \u091a\u0932\u0947 \u092a\u0921\u093c\u0947 \u0939\u0948\u0902\u0964 \u0935\u0939 \u0920\u093e\u0915\u0930\u0947 \u092a\u0930\u093f\u0935\u093e\u0930 \u0915\u0947 \u092c\u093e\u0926 \u0936\u093f\u0935\u0938\u0947\u0928\u093e \u0915\u0947 \u0938\u092c\u0938\u0947 \u0915\u2026", "url": "https://navbharattimes.indiatimes.com/metro/mumbai/politics/maharashtra-political-crisis-was-eknath-shinde-the-weakest-link-in-the-ncp-shiv-sena-congress-alliance/articleshow/92363880.cms", "urlToImage": "https://navbharattimes.indiatimes.com/photo/msid-92363880,imgsize-32312/pic.jpg", "publishedAt": "2022-06-21T12:31:26Z", "content": "Curated by \r\n| . | Updated: Jun 21, 2022, 6:10 PM\r\nNavbharat Times News App: - , , , , -... NBT Web Title : maharashtra political crisis was eknath shinde the weakest link in the ncp-shiv sena-congre\u2026 [+339 chars]"}, {"source": {"id": "the-times-of-india", "name": "The Times of India"}, "author": "Sneha Hiro", "title": "Pics of Anil that prove he is aging backward", "description": "9 Pictures of 'JugJugg Jeeyo' star Anil Kapoor that prove he is aging backward", "url": "https://timesofindia.indiatimes.com/entertainment/hindi/web-stories/9-pictures-of-jugjugg-jeeyo-star-anil-kapoor-that-prove-he-is-aging-backward/photostory/92363561.cms", "urlToImage": "https://static.toiimg.com/thumb/msid-92363598,width-900,height-1200,imgsize-52358,resizemode-6.cms", "publishedAt": "2022-06-21T12:30:00Z", "content": "This picture of Anil Kapoor makes us scream out loud - good looks, good looks, and good looks!"}, {"source": {"id": "the-times-of-india", "name": "The Times of India"}, "author": "PTI", "title": "Delhi to shut down all units dealing in single-use plastic items from Jul 1", "description": "\"We have issued strict directions to manufacturers, stockists, suppliers and distributors of single-use plastic items to ensure zero inventory of the 19 SUP items. Within the first week of July, those who do not maintain a zero inventory will be shut down,\" a\u2026", "url": "https://economictimes.indiatimes.com/news/india/delhi-to-shut-down-all-units-dealing-in-single-use-plastic-items-from-jul-1/articleshow/92364154.cms", "urlToImage": "https://img.etimg.com/thumb/msid-92364278,width-1070,height-580,imgsize-74302,overlay-economictimes/photo.jpg", "publishedAt": "2022-06-21T12:26:55Z", "content": "The Delhi Environment Department will run a campaign to ensure compliance with the ban on 19 identified single-use plastic (SUP) items starting July 1 and close down all manufacturers, suppliers, sto\u2026 [+2184 chars]"}, {"source": {"id": "the-times-of-india", "name": "The Times of India"}, "author": "Reuters", "title": "Oil prices climb $2 on strong demand, tight supply", "description": "\"We expect oil demand to improve further, benefiting from the reopening of China, summer travel in the northern hemisphere and the weather getting warmer in the Middle East. With supply growth lagging demand growth over the coming months, we continue to expec\u2026", "url": "https://economictimes.indiatimes.com/markets/commodities/news/oil-prices-climb-2-on-strong-demand-tight-supply/articleshow/92364132.cms", "urlToImage": "https://img.etimg.com/thumb/msid-92364143,width-1070,height-580,imgsize-147014,overlay-etmarkets/photo.jpg", "publishedAt": "2022-06-21T12:25:43Z", "content": "Oil prices rose almost $2 on Tuesday on high summer fuel demand while supplies remain tight because of sanctions on Russian oil after its invasion of Ukraine.\r\nBrent crude rose $1.80, or 1.6%, to $11\u2026 [+2251 chars]"}, {"source": {"id": "the-times-of-india", "name": "The Times of India"}, "author": "Mirror Now", "title": "Maharashtra political crisis: Ajay Chaudhary to replace Eknath Shinde as Shiv Sena Legislative party leader", "description": "The Shiv Sena on Monday decided to remove its cabinet minister Eknath Shinde as its Legislative party leader and Sewri MLA Ajay Chaudhary will be the new Shiv Sena Legislative party leader, sources said. This comes after Shinde and some Shiv Sena MLAs became \u2026", "url": "https://economictimes.indiatimes.com/news/politics-and-nation/maharashtra-political-crisis-ajay-chaudhary-to-replace-eknath-shinde-as-shiv-sena-legislative-party-leader/videoshow/92364124.cms", "urlToImage": "https://img.etimg.com/thumb/msid-92364124,width-1070,height-580,overlay-economictimes/photo.jpg", "publishedAt": "2022-06-21T12:25:23Z", "content": "The Shiv Sena on Monday decided to remove its cabinet minister Eknath Shinde as its Legislative party leader and Sewri MLA Ajay Chaudhary will be the new Shiv Sena Legislative party leader, sources s\u2026 [+350 chars]"}, {"source": {"id": "the-times-of-india", "name": "The Times of India"}, "author": "ET Spotlight Special", "title": "JEE Main 2022: Admit card for June session is out. Here's how you can download it", "description": "This year, the JEE Main 2022 Examination Season 1 is scheduled to be held on June 23 and 29, 2022. Candidates appearing for the JEE Main Examination 2022 for the June session are required to bring their self-declaration form along with the JEE Main admit card\u2026", "url": "https://economictimes.indiatimes.com/news/new-updates/jee-main-2022-admit-card-for-june-session-is-out-heres-how-you-can-download-it/articleshow/92362268.cms", "urlToImage": "https://img.etimg.com/thumb/msid-92364083,width-1070,height-580,imgsize-18286,overlay-economictimes/photo.jpg", "publishedAt": "2022-06-21T12:24:28Z", "content": "The National Testing Agency has issued the admit cards to be downloaded for the Joint Entrance Examination Main for June 2022. Applicants for JEE Main 2022 can check and download their correct admit \u2026 [+1781 chars]"}, {"source": {"id": "the-times-of-india", "name": "The Times of India"}, "author": "Saikat Das", "title": "Bond investors appear bearish on Vedanta Resources", "description": "Vedanta would look into buying an incremental 5% stake in Hindustan Zinc from the government, but the rest of the sovereign stake will be sold in the open market.", "url": "https://economictimes.indiatimes.com/markets/bonds/bond-investors-appear-bearish-on-vedanta-resources/articleshow/92363883.cms", "urlToImage": "https://img.etimg.com/thumb/msid-92363972,width-1070,height-580,imgsize-36884,overlay-etmarkets/photo.jpg", "publishedAt": "2022-06-21T12:21:10Z", "content": "Bond investors currently appear bearish on Vedanta Resources (VRL), pushing yields on the infrequently traded debt to as high as 18%, amid a sell-off globally in commodities and in the aftermath of t\u2026 [+4094 chars]"}, {"source": {"id": "the-times-of-india", "name": "The Times of India"}, "author": "Vanya Gautam", "title": "At Almost \u20b95,000 Crore, RBI Spends Highest Amount On Banknote Printing Since Demonetisation", "description": "In the financial year 2021-22, the RBI spent \u20b94,984.8 crores on security printing of banknotes purchased from printing presses. At\u00a0\u20b94,012.1 crores,\u00a0the spending was about 25% lower than the previous period.\u00a0It is noteworthy that\u00a0the total supply of banknotes \u2026", "url": "https://www.indiatimes.com/worth/news/rbi-spent-nearly-5000-crore-rupees-on-banknote-printing-in-fy22-572767.html", "urlToImage": "https://im.indiatimes.in/content/2022/Jun/Reserve-Bank-Of-India-Spent-49848-Crore-On-Banknote-Printing-In-FY22_62b1adbb97bd8.jpg", "publishedAt": "2022-06-21T12:20:05Z", "content": "In the financial year 2021-22, the RBI spent 4,984.8 crores on security printing of banknotes purchased from printing presses. At\u00a04,012.1 crores,\u00a0the spending was about 25% lower than the previous pe\u2026 [+3767 chars]"}, {"source": {"id": "the-times-of-india", "name": "The Times of India"}, "author": "ET Spotlight Special", "title": "Tamil Nadu shop owner buys car with transaction in all Rs 10 coins", "description": "He told the media that his mother runs a small shop in his hometown in Arur, Dharmapuri, and people there do not accept Rs 10 coins. Because of this, they could not exchange the Rs 10 coins with their customers, and this had led to a huge collection of Rs 10 \u2026", "url": "https://economictimes.indiatimes.com/news/new-updates/tamil-nadu-shop-owner-buys-car-with-transaction-in-all-rs-10-coins/articleshow/92363640.cms", "urlToImage": "https://img.etimg.com/thumb/msid-92363790,width-1070,height-580,imgsize-43102,overlay-economictimes/photo.jpg", "publishedAt": "2022-06-21T12:15:25Z", "content": "A man named Vetrivel in Tamil Nadus Dharmapuri area recently bought a car worth Rs 6 lakh by using 60,000 coins, each one of Rs 10. He wanted to create awareness among people to give equal importance\u2026 [+882 chars]"}, {"source": {"id": "the-times-of-india", "name": "The Times of India"}, "author": "PTI", "title": "Finance ministry collaborates with CBC for Capacity Enhancement Plan on infra projects execution", "description": "Under this capacity building initiative of DEA, the 9th programme on the topic 'Public Private Partnerships (PPPs)' was started on June 20, 2022 with 37 participants,  said.", "url": "https://economictimes.indiatimes.com/news/economy/policy/finance-ministry-collaborates-with-cbc-for-capacity-enhancement-plan-on-infra-projects-execution/articleshow/92363774.cms", "urlToImage": "https://img.etimg.com/thumb/msid-92363855,width-1070,height-580,imgsize-52106,overlay-economictimes/photo.jpg", "publishedAt": "2022-06-21T12:12:57Z", "content": "The Department of Economic Affairs (DEA), under the finance ministry, in collaboration with the Capacity Building Commission (CBC) has framed a Capacity Enhancement Plan (CEP) for driving relevant ca\u2026 [+1783 chars]"}, {"source": {"id": "the-times-of-india", "name": "The Times of India"}, "author": "AFP", "title": "Putin says 'proud' of Russian troops in Ukraine", "description": "And \"in the face of new threats and risks, we will further develop and strengthen our armed forces\", Putin said, promising the new Sarmat intercontinental ballistic missile would be commissioned by the end of the year.", "url": "https://economictimes.indiatimes.com/news/international/world-news/putin-says-proud-of-russian-troops-in-ukraine/articleshow/92363747.cms", "urlToImage": "https://img.etimg.com/thumb/msid-92363798,width-1070,height-580,imgsize-87628,overlay-economictimes/photo.jpg", "publishedAt": "2022-06-21T12:12:20Z", "content": "Russian President Vladimir Putin said on Tuesday he was \"proud\" of the action of his soldiers in Ukraine, where Moscow says it is conducting a military operation. \r\n\"We are proud that during the spec\u2026 [+823 chars]"}, {"source": {"id": "the-times-of-india", "name": "The Times of India"}, "author": "PTI", "title": "No need to panic but exercise caution: Experts amid rise in Covid cases in Delhi", "description": "Doctors at leading government and private hospitals here concurred that though it wasn't a \"panic situation\" but cautioned against lowering the guard, while flagging that many people had stopped wearing mask or stopped putting it on properly at public places,\u2026", "url": "https://economictimes.indiatimes.com/news/india/no-need-to-panic-but-exercise-caution-experts-amid-rise-in-covid-cases-in-delhi/articleshow/92363690.cms", "urlToImage": "https://img.etimg.com/thumb/msid-92363824,width-1070,height-580,imgsize-184198,overlay-economictimes/photo.jpg", "publishedAt": "2022-06-21T12:10:24Z", "content": "Amid a spike in Covid cases in Delhi, experts on Tuesday said there was no need to panic as the number of coronavirus patients getting hospitalised was still on the lower side but asserted that every\u2026 [+4835 chars]"}, {"source": {"id": "the-times-of-india", "name": "The Times of India"}, "author": null, "title": "\u0938\u094b\u092e\u0935\u093e\u0930 \u0915\u094b \u091f\u0942\u091f \u0915\u0947 \u091a\u0942\u0930 \u0939\u0941\u0908 '\u0938\u092e\u094d\u0930\u093e\u091f \u092a\u0943\u0925\u094d\u200d\u0935\u0940\u0930\u093e\u091c', '\u092d\u0942\u0932 \u092d\u0941\u0932\u0948\u092f\u093e 2' \u0915\u0940 \u091c\u093f\u0926 \u0915\u0947 \u0906\u0917\u0947 '\u0928\u093f\u0915\u092e\u094d\u200d\u092e\u093e' \u092d\u0940 \u092e\u091c\u092c\u0942\u0930", "description": "'\u0928\u093f\u0915\u092e\u094d\u200d\u092e\u093e' \u0930\u093f\u0932\u0940\u091c \u0915\u0947 \u091a\u094c\u0925\u0947 \u0939\u0940 \u0926\u093f\u0928 \u092c\u0949\u0915\u094d\u200d\u0938 \u0911\u092b\u093f\u0938 \u092a\u0930 \u0927\u0921\u093c\u093e\u092e \u0939\u094b \u0917\u0908 \u0939\u0948\u0964 \u0905\u0915\u094d\u0937\u092f \u0915\u0941\u092e\u093e\u0930 \u0915\u0940 '\u0938\u092e\u094d\u0930\u093e\u091f \u092a\u0943\u0925\u094d\u200d\u0935\u0940\u0930\u093e\u091c' 18 \u0926\u093f\u0928\u094b\u0902 \u092e\u0947\u0902 \u0938\u093f\u0930\u094d\u092b 68 \u0915\u0930\u094b\u0921\u093c \u0930\u0941\u092a\u092f\u0947 \u0915\u092e\u093e \u092a\u093e\u0908 \u0939\u0948\u0964 \u091c\u092c\u0915\u093f '\u092d\u0942\u0932 \u092d\u0941\u0932\u0948\u092f\u093e 2' \u0928\u0947 32\u0935\u0947\u0902 \u0926\u093f\u0928 \u092d\u0940 \u0938\u092c\u0938\u0947 \u0905\u0927\u200d\u093f\u0915 \u0915\u092e\u093e\u0908 \u0915\u0940 \u0939\u0948\u0964", "url": "https://navbharattimes.indiatimes.com/movie-masti/box-office/monday-box-office-report-nikamma-crashes-on-fourth-day-bhool-bhulaiyaa-2-day-32-earning-is-better-than-samrat-prithviraj-day-18-collection/articleshow/92363545.cms", "urlToImage": "https://navbharattimes.indiatimes.com/photo/msid-92363568,imgsize-123/pic.jpg", "publishedAt": "2022-06-21T12:09:05Z", "content": "' 2' 32 , ' 2' 70 , ' ' '' '' 20 ' ' 18 50 \r\n ' 2' - , , , Bhool Bhulaiyaa 2 32 178.18 ' ' 80-85 ' 2' Box Office , 180 \r\nNeetu Kapoor - ! ... ' 2' - 90.78 - 49.23 - 20.47 - 12.00 - 1.00 - 1.75 - 2.25\u2026 [+205 chars]"}, {"source": {"id": "the-times-of-india", "name": "The Times of India"}, "author": "Reuters", "title": "Yen dives, hits new 24-year low vs dollar", "description": "The yen dropped 0.8% to a 24-year low of 136.18 per dollar , extending losses after the Bank of Japan on Friday dashed any mild expectations of a change in policy and continued to stand alone in its commitment to ultra-easy monetary settings.", "url": "https://economictimes.indiatimes.com/markets/forex/yen-dives-hits-new-24-year-low-vs-dollar/articleshow/92363607.cms", "urlToImage": "https://img.etimg.com/thumb/msid-92363625,width-1070,height-580,imgsize-125866,overlay-etmarkets/photo.jpg", "publishedAt": "2022-06-21T12:06:49Z", "content": "The Japanese yen plunged on Tuesday to the lowest since October 1998, as the Bank of Japan's ultra-loose monetary policy stance continued to weigh.\r\nThe yen dropped 0.8% to a 24-year low of 136.18 pe\u2026 [+299 chars]"}, {"source": {"id": "the-times-of-india", "name": "The Times of India"}, "author": "AFP", "title": "Oil turbulence could last five years, ExxonMobil boss warns", "description": "Energy markets have been roiled by the Ukraine war as Russia has reduced some exports and faced sanctions while Europe has announced plans to wean itself off dependency on Russian fossil fuels in coming years.", "url": "https://economictimes.indiatimes.com/news/international/business/oil-turbulence-could-last-five-years-exxonmobil-boss-warns/articleshow/92363606.cms", "urlToImage": "https://img.etimg.com/thumb/msid-92363713,width-1070,height-580,imgsize-48626,overlay-economictimes/photo.jpg", "publishedAt": "2022-06-21T12:06:45Z", "content": "Consumers must be prepared to endure up to five years of turbulent oil markets, the head of ExxonMobil said Tuesday, citing under-investment and the coronavirus pandemic.\r\nEnergy markets have been ro\u2026 [+3061 chars]"}, {"source": {"id": "the-times-of-india", "name": "The Times of India"}, "author": null, "title": "\u090f\u0915\u0928\u093e\u0925 \u0936\u093f\u0902\u0926\u0947 \u0915\u093f\u0902\u0917\u092e\u0947\u0915\u0930, \u092b\u0921\u0923\u0935\u0940\u0938 \u0915\u0947 \u0938\u093e\u0925 \u092e\u093f\u0932\u0915\u0930 \u092c\u0928\u093e \u0932\u0947\u0902 \u0938\u0930\u0915\u093e\u0930... \u0915\u093e\u0928\u092a\u0941\u0930 \u092e\u0947\u0902 \u092c\u094b\u0932\u0947 \u0930\u093e\u092e\u0926\u093e\u0938 \u0906\u0920\u0935\u0932\u0947", "description": "\u0915\u0947\u0902\u0926\u094d\u0930\u0940\u092f \u092e\u0902\u0924\u094d\u0930\u0940 \u0930\u093e\u092e\u0926\u093e\u0938 \u0906\u0920\u0935\u0932\u0947 \u0928\u0947 \u092e\u0902\u0917\u0932\u0935\u093e\u0930 \u0915\u094b \u0915\u093e\u0928\u092a\u0941\u0930 \u092e\u0947\u0902 \u0915\u0939\u093e \u0915\u093f \u090f\u0915\u0928\u093e\u0925 \u0936\u093f\u0902\u0926\u0947 \u092e\u0939\u093e\u0930\u093e\u0937\u094d\u091f\u094d\u0930 \u092e\u0947\u0902 \u0915\u093f\u0902\u0917\u092e\u0947\u0915\u0930 \u0915\u0940 \u092d\u0942\u092e\u093f\u0915\u093e \u092e\u0947\u0902 \u0939\u0948\u0902\u0964 \u0909\u0928\u094d\u0939\u0947\u0902 \u092b\u0921\u0923\u0935\u0940\u0938 \u0915\u0947 \u0938\u093e\u0925 \u092e\u093f\u0932\u0915\u0930 \u0938\u0930\u0915\u093e\u0930 \u092c\u0928\u093e\u0928\u0940 \u091a\u093e\u0939\u093f\u090f\u0964 \u0909\u0928\u094d\u0939\u094b\u0902\u0928\u0947 \u0909\u0926\u094d\u0927\u0935 \u0920\u093e\u0915\u0930\u0947 \u092a\u0930 \u0906\u0930\u094b\u092a \u0932\u0917\u093e\u092f\u093e \u0915\u093f \u0909\u0928\u094d\u0939\u094b\u0902\u0928\u0947 \u0938\u0902\u091c\u092f \u0930\u093e\u0909\u0924 \u0915\u0947 \u091a\u0932\u0924\u0947 \u0915\u093e\u0902\u0917\u094d\u0930\u0947\u0938 \u0915\u0947 \u0938\u093e\u0925 \u0917\u0920\u092c\u0902\u0927\u0928 \u0915\u093f\u092f\u093e\u0964", "url": "https://navbharattimes.indiatimes.com/state/uttar-pradesh/kanpur/eknath-shinde-kingmaker-form-government-with-devendra-fadnavis-said-ramdas-athawale-in-kanpur/articleshow/92363600.cms", "urlToImage": "https://navbharattimes.indiatimes.com/photo/msid-92363600,imgsize-32318/pic.jpg", "publishedAt": "2022-06-21T12:06:44Z", "content": ", 36 \r\n 2013 \r\n2014 RPI 36 \r\n , 2022 RPI , 26 \r\nNavbharat Times News App: - , , , , -... NBT Web Title : eknath shinde kingmaker form government with devendra fadnavis said ramdas athawale in kanpurH\u2026 [+339 chars]"}, {"source": {"id": "the-times-of-india", "name": "The Times of India"}, "author": "PTI", "title": "Hopeful for conclusion of India-UK free trade agreement by Diwali: Piyush Goyal", "description": "The minister for commerce and industry and textiles said that the government is moving ahead on free trade pacts with Canada, European Union and the UK. Moreover, Goyal informed that Australia, Israel and the Gulf Cooperation Countries have expressed interest\u2026", "url": "https://economictimes.indiatimes.com/news/economy/foreign-trade/hopeful-for-conclusion-of-india-uk-free-trade-agreement-by-diwali-piyush-goyal/articleshow/92363542.cms", "urlToImage": "https://img.etimg.com/thumb/msid-92363523,width-1070,height-580,imgsize-1480776,overlay-economictimes/photo.jpg", "publishedAt": "2022-06-21T12:04:20Z", "content": "Union minister Piyush Goyal has expressed hope that the free trade agreement between India and the United Kingdom will be concluded by Diwali.\r\nThe minister for commerce and industry and textiles sai\u2026 [+1587 chars]"}, {"source": {"id": "the-times-of-india", "name": "The Times of India"}, "author": "ET Spotlight Special", "title": "World Music Day 2022:Top quotes, wishes and messages", "description": "Enthusiasts worldwide observe this day to encourage upcoming musicians to take up music as a career and create awareness about it. The festival, originally known as F\u00eate de la Musique, celebrates musical art and creativity and is observed in over 1,000 cities\u2026", "url": "https://economictimes.indiatimes.com/news/new-updates/world-music-day-2022top-quotes-wishes-and-messages/articleshow/92363398.cms", "urlToImage": "https://img.etimg.com/thumb/msid-92363433,width-1070,height-580,imgsize-63480,overlay-economictimes/photo.jpg", "publishedAt": "2022-06-21T12:02:30Z", "content": "World Music Day is celebrated today, June 21. Enthusiasts worldwide observe this day to encourage upcoming musicians to take up music as a career and create awareness about it. The festival, original\u2026 [+1598 chars]"}]}